{
	"id": "7f6b530a-4650-4143-b7c4-bbe037fcbb51",
	"prevId": "769564ef-06df-4c89-8d31-ba72782ec0b0",
	"version": "5",
	"dialect": "pg",
	"tables": {
		"users": {
			"name": "users",
			"schema": "",
			"columns": {
				"id": {
					"name": "id",
					"type": "serial",
					"primaryKey": true,
					"notNull": true
				},
				"email": {
					"name": "email",
					"type": "varchar(256)",
					"primaryKey": false,
					"notNull": false
				},
				"first_name": {
					"name": "first_name",
					"type": "text",
					"primaryKey": false,
					"notNull": false
				},
				"last_name": {
					"name": "last_name",
					"type": "text",
					"primaryKey": false,
					"notNull": false
				},
				"full_name": {
					"name": "full_name",
					"type": "text",
					"primaryKey": false,
					"notNull": false
				},
				"phone": {
					"name": "phone",
					"type": "varchar(256)",
					"primaryKey": false,
					"notNull": false
				}
			},
			"indexes": {},
			"foreignKeys": {},
			"compositePrimaryKeys": {},
			"uniqueConstraints": {
				"users_id_unique": {
					"name": "users_id_unique",
					"nullsNotDistinct": false,
					"columns": ["id"]
				}
			}
		}
	},
	"enums": {},
	"schemas": {},
	"_meta": {
		"columns": {},
		"schemas": {},
		"tables": {}
	}
}
